{
  "solution": {
    "zmod-ember": {
      "impact": "patch",
      "oldVersion": "0.3.0",
      "newVersion": "0.3.1",
      "tagName": "latest",
      "constraints": [
        {
          "impact": "patch",
          "reason": "Appears in changelog section :bug: Bug Fix"
        },
        {
          "impact": "patch",
          "reason": "Appears in changelog section :house: Internal"
        }
      ],
      "pkgJSONPath": "./package.json"
    }
  },
  "description": "## Release (2026-04-21)\n\n* zmod-ember 0.3.1 (patch)\n\n#### :bug: Bug Fix\n* `zmod-ember`\n  * [#10](https://github.com/NullVoxPopuli/zmod-ember/pull/10) Add tests for finding and changing Glimmer template comment content ([@NullVoxPopuli-ai-agent](https://github.com/NullVoxPopuli-ai-agent))\n\n#### :house: Internal\n* `zmod-ember`\n  * [#12](https://github.com/NullVoxPopuli/zmod-ember/pull/12) Update release-plan ([@NullVoxPopuli](https://github.com/NullVoxPopuli))\n\n#### Committers: 2\n- @NullVoxPopuli's reduced-access machine account for AI usage ([@NullVoxPopuli-ai-agent](https://github.com/NullVoxPopuli-ai-agent))\n- [@NullVoxPopuli](https://github.com/NullVoxPopuli)\n"
}
